astropixie_hr/__init__.py
astropixie_hr/config.py
astropixie_hr/science.py
astropixie_hr/visual.py
astropixie_hr-0.1.0.dist-info/DESCRIPTION.rst
astropixie_hr-0.1.0.dist-info/METADATA
astropixie_hr-0.1.0.dist-info/RECORD
astropixie_hr-0.1.0.dist-info/WHEEL
astropixie_hr-0.1.0.dist-info/metadata.json
astropixie_hr-0.1.0.dist-info/top_level.txt
