Metadata-Version: 2.0
Name: astropixie-hr
Version: 0.1.0
Summary: LSST EPO Hertzsprung-Russell (HR) Diagram library.
Home-page: https://github.com/lsst-epo/vela/astropixie-hr
Author: LSST EPO Team
Author-email: epo-team@lists.lsst.org
License: MIT
Platform: UNKNOWN
Requires-Dist: astropixie
Requires-Dist: astropy
Requires-Dist: astroquery
Requires-Dist: bokeh
Requires-Dist: numpy
Requires-Dist: pandas
Requires-Dist: pytest
Requires-Dist: scipy
